pg0/__init__.py
pg0/py.typed
pg0/bin/pg0
pg0_embedded-0.12.0.dist-info/METADATA
pg0_embedded-0.12.0.dist-info/WHEEL
pg0_embedded-0.12.0.dist-info/RECORD
