Metadata-Version: 2.4
Name: pg0-embedded
Version: 0.12.0
Summary: Python API for pg0 - embedded PostgreSQL
Project-URL: Homepage, https://github.com/vectorize-io/pg0
Project-URL: Repository, https://github.com/vectorize-io/pg0
License-Expression: MIT
Keywords: database,embedded,pgvector,postgresql
Classifier: Development Status :: 4 - Beta
Classifier: Intended Audience :: Developers
Classifier: License :: OSI Approved :: MIT License
Classifier: Programming Language :: Python :: 3
Classifier: Programming Language :: Python :: 3.8
Classifier: Programming Language :: Python :: 3.9
Classifier: Programming Language :: Python :: 3.10
Classifier: Programming Language :: Python :: 3.11
Classifier: Programming Language :: Python :: 3.12
Requires-Python: >=3.8
Provides-Extra: dev
Requires-Dist: pytest>=8.0.0; extra == 'dev'
